Femut/Femut_CUI.py
Femut/General.py
Femut/__init__.py
Femut-1.0.3.dist-info/LICENSE
Femut-1.0.3.dist-info/METADATA
Femut-1.0.3.dist-info/WHEEL
Femut-1.0.3.dist-info/top_level.txt
Femut-1.0.3.dist-info/RECORD
